odoo/addons/website_kubectl/LICENSE
odoo/addons/website_kubectl/README.rst
odoo/addons/website_kubectl/__init__.py
odoo/addons/website_kubectl/__manifest__.py
odoo/addons/website_kubectl/controllers/__init__.py
odoo/addons/website_kubectl/controllers/main.py
odoo/addons/website_kubectl/images/screen.png
odoo/addons/website_kubectl/models/__init__.py
odoo/addons/website_kubectl/models/kubectl_cluster.py
odoo/addons/website_kubectl/static/description/icon.png
odoo/addons/website_kubectl/static/description/index.html
odoo/addons/website_kubectl/tests/TEST_INSTRUCTIONS.rst
odoo/addons/website_kubectl/views/kubectl_cluster_views.xml
odoo/addons/website_kubectl/views/website_kubectl_cluster_templates.xml
odoo_addon_website_kubectl-18.0.1.0.0.dist-info/METADATA
odoo_addon_website_kubectl-18.0.1.0.0.dist-info/WHEEL
odoo_addon_website_kubectl-18.0.1.0.0.dist-info/top_level.txt
odoo_addon_website_kubectl-18.0.1.0.0.dist-info/RECORD
